dpy_button_utils/__init__.py
dpy_button_utils/confirmation.py
dpy_button_utils/models.py
dpy_button_utils/multiplechoice.py
dpy_button_utils/paginator.py
dpy_button_utils/utils.py
dpy_button_utils-1.1.0.dist-info/LICENSE.md
dpy_button_utils-1.1.0.dist-info/METADATA
dpy_button_utils-1.1.0.dist-info/WHEEL
dpy_button_utils-1.1.0.dist-info/top_level.txt
dpy_button_utils-1.1.0.dist-info/RECORD
